satveg_api/__init__.py
satveg_api/satveg_api.py
satveg_api-2.0.1.dist-info/METADATA
satveg_api-2.0.1.dist-info/WHEEL
satveg_api-2.0.1.dist-info/top_level.txt
satveg_api-2.0.1.dist-info/RECORD
