Metadata-Version: 2.1
Name: satveg-api
Version: 2.0.1
Author: Vitor Leonardo Pauloski
Project-URL: Source code, https://github.com/vitorpauloski/satveg-api
Requires-Python: >=3.8
Requires-Dist: pandas (>=1.4.3)
Requires-Dist: requests (>=2.28.1)
